{
    "lastupdated": "2025-10-17T13:38:46.000Z",
    "dbtitle": "British TV",
    "filename": "ftv-british.json",
    "dbversion": "1.0",
    "author": "Free TV",
    "email": "support@freetv.today",
    "link": "https://freetv.today",
    "shows": [
        {
            "category": "comedy",
            "status": "active",
            "identifier": "allo-allo",
            "title": "'Allo 'Allo",
            "desc": "In France during World War II, Ren\u00e9 Artois runs a small caf\u00e9 where Resistance fighters, Gestapo men, German Army officers and escaped Allied POWs interact daily, ignorant of one another's true identity or presence, exasperating Ren\u00e9.",
            "start": "1982",
            "end": "1992",
            "imdb": "tt0086659"
        },
        {
            "category": "comedy",
            "status": "active",
            "identifier": "black-books-tv-series-2000-2004",
            "title": "Black Books",
            "desc": "Bernard Black runs a book shop, though his customer service skills leave something to be desired. He hires Manny as an employee. Fran runs the shop next door. Between the three of them many adventures ensue.",
            "start": "2000",
            "end": "2004",
            "imdb": "tt0262150"
        },
        {
            "category": "comedy",
            "status": "active",
            "identifier": "blackadder-remastered",
            "title": "Blackadder",
            "desc": "In the Middle Ages, Prince Edmund the Black Adder constantly schemes and endeavors to seize the crown from his father and brother.",
            "start": "1982",
            "end": "1989",
            "imdb": "tt0084988"
        },
        {
            "category": "comedy",
            "status": "active",
            "identifier": "dadsarmythecompletecollection",
            "title": "Dad's Army",
            "desc": "A ragtag group of Home Guard volunteers prepare for an imminent German invasion during World War II.",
            "start": "1968",
            "end": "1977",
            "imdb": "tt0062552"
        },
        {
            "category": "comedy",
            "status": "active",
            "identifier": "father-ted-2005",
            "title": "Father Ted",
            "desc": "Three misfit priests and their housekeeper live on Craggy Island, not the peaceful and quiet part of Ireland that it seems to be.",
            "start": "1995",
            "end": "1998",
            "imdb": "tt0111958"
        },
        {
            "category": "comedy",
            "status": "active",
            "identifier": "FawltyTowers",
            "title": "Fawlty Towers",
            "desc": "Hotel owner Basil Fawlty's incompetence, short fuse, and arrogance form a combination that ensures accidents and trouble are never far away.",
            "start": "1975",
            "end": "1979",
            "imdb": "tt0072500"
        },
        {
            "category": "comedy",
            "status": "active",
            "identifier": "fs-series",
            "title": "French and Saunders",
            "desc": "Comedy duo Dawn French and Jennifer Saunders satirically present aspects of British life, films such as Batman Forever and Pulp Fiction.",
            "start": "1987",
            "end": "2017",
            "imdb": "tt0092355"
        },
        {
            "category": "comedy",
            "status": "active",
            "identifier": "keeping-up-appearances_202402",
            "title": "Keeping Up Appearances",
            "desc": "A snobbish housewife is determined to climb the social ladder, in spite of her family's working class connections and the constant chagrin of her long suffering husband.",
            "start": "1990",
            "end": "1995",
            "imdb": "tt0098837"
        },
        {
            "category": "comedy",
            "status": "active",
            "identifier": "lastofthesummerwine",
            "title": "Last Of The Summer Wine",
            "desc": "Three old men from Yorkshire who have never grown up face the trials of their fellow town citizens and everyday life and stay young by reminiscing about the days of their youth and attempting feats not common to the elderly.",
            "start": "1973",
            "end": "2010",
            "imdb": "tt0069602"
        },
        {
            "category": "comedy",
            "status": "active",
            "identifier": "mpfc-remastered_hd",
            "title": "Monty Python's Flying Circus",
            "desc": "The original surreal sketch comedy showcase for the Monty Python troupe.",
            "start": "1969",
            "end": "1974",
            "imdb": "tt0063929"
        },
        {
            "category": "comedy",
            "status": "active",
            "identifier": "mr-bean-the-complete-live-action-series",
            "title": "Mr. Bean",
            "desc": "Bumbling, childlike Mr. Bean has trouble completing the simplest of day-to-day tasks, but his perseverance and resourcefulness frequently allow him to find ingenious ways around problems.",
            "start": "1990",
            "end": "1995",
            "imdb": "tt0096657"
        },
        {
            "category": "comedy",
            "status": "active",
            "identifier": "mrs.-browns-boys-s-03-e-11-mammys-christmas-punch",
            "title": "Mrs. Brown's Boys",
            "desc": "A comedy centered on a loud-mouthed Irish matriarch whose favorite pastime is meddling in the lives of her six children.",
            "start": "2011",
            "end": "2014",
            "imdb": "tt1819022"
        },
        {
            "category": "comedy",
            "status": "active",
            "identifier": "bbc-red-dwarf",
            "title": "Red Dwarf",
            "desc": "The adventures of the last human alive and his friends, stranded 3 million years into deep space on the mining ship Red Dwarf.",
            "start": "1988",
            "end": "2020",
            "imdb": "tt0094535"
        },
        {
            "category": "comedy",
            "status": "active",
            "identifier": "ripping-yarns-1976-79",
            "title": "Ripping Yarns",
            "desc": "This show is a collection of tales that make for \"ripping good\" television. Sir Michael Palin played a different lead character in each yarn.",
            "start": "1976",
            "end": "1979",
            "imdb": "tt0075568"
        },
        {
            "category": "comedy",
            "status": "active",
            "identifier": "the-benny-hill-show",
            "title": "The Benny Hill Show",
            "desc": "A skit based show with Benny Hill, often containing smutty humour.",
            "start": "1969",
            "end": "1989",
            "imdb": "tt0063869"
        },
        {
            "category": "comedy",
            "status": "active",
            "identifier": "vicar-of-dibley-s-01-e-01-arrival.avi",
            "title": "The Vicar of Dibley",
            "desc": "A boisterous female minister comes to serve in an eccentrically conservative village's church.",
            "start": "1994",
            "end": "2000",
            "imdb": "tt0108981"
        },
        {
            "category": "comedy",
            "status": "active",
            "identifier": "the-young-ones-s-01-ep-04-bomb",
            "title": "The Young Ones",
            "desc": "The crazy and sometimes surreal comedic adventures of four very different students in Thatcher's Britain.",
            "start": "1982",
            "end": "1984",
            "imdb": "tt0083505"
        },
        {
            "category": "comedy",
            "status": "active",
            "identifier": "yes-minister-1980-1984",
            "title": "Yes Minister",
            "desc": "The Right Honorable James Hacker has landed the plum job of Cabinet Minister to the Department of Administration. At last he is in a position of power and can carry out some long-needed reforms, or so he thinks.",
            "start": "1980",
            "end": "1984",
            "imdb": "tt0080306"
        },
        {
            "category": "cooking",
            "status": "active",
            "identifier": "two.-fat.-ladies.-s-01-e-04.-cakes.and.-baking.-sdtv.x-265-aac",
            "title": "Two Fat Ladies",
            "desc": "Clarissa and Jennifer are two long-time friends who enjoy driving on their motorcycle and cooking ethnic foods according to where they live.",
            "start": "1996",
            "end": "1999",
            "imdb": "tt0169499"
        },
        {
            "category": "Drama",
            "status": "active",
            "identifier": "01-rumpole-of-the-bailey-s-01-e-01-rumpole-and-the-younger-generation-1",
            "title": "Rumpole Of The Bailey",
            "desc": "The cases of a portly and eccentric criminal law barrister.",
            "start": "1978",
            "end": "1992",
            "imdb": "tt0078680"
        },
        {
            "category": "Drama",
            "status": "active",
            "identifier": "the-professionals-complete-series-1977",
            "title": "The Professionals",
            "desc": "Bodie and Doyle, senior agents of the British intelligence service CI5 (Criminal Intelligence 5), and their handler George Cowley fight terrorism and similar high-level crimes.",
            "start": "1977",
            "end": "1983",
            "imdb": "tt0075561"
        },
        {
            "category": "kids",
            "status": "active",
            "identifier": "charlie-chalk-the-complete-series-1988-89",
            "title": "Charlie Chalk",
            "desc": "A clown named Charlie Chalk arrives on the island of Merrytwit after falling asleep on his boat. He befriends the inhabitants of the island and gets into many adventures.",
            "start": "1988",
            "end": "1989",
            "imdb": "tt0436999"
        },
        {
            "category": "kids",
            "status": "active",
            "identifier": "enchanted-world-of-brambly-hedge-1996-2000",
            "title": "Brambly Hedge",
            "desc": "The enchanting tales of a community of field mice living in secret in a brambly hedgerow. The full name of the show is \"The Enchanted World of Brambly Hedge\".",
            "start": "1996",
            "end": "2000",
            "imdb": "tt0796568"
        },
        {
            "category": "kids",
            "status": "active",
            "identifier": "little-miss-1983-bbc-tv-series-the-complete-collection",
            "title": "Little Miss",
            "desc": "The adventures of the Little Miss characters created by Roger Hargreaves as female counterparts to the original Mr Men. The personality and appearance of each character matches their name.",
            "start": "1983",
            "end": "1983",
            "imdb": "tt0299341"
        },
        {
            "category": "kids",
            "status": "active",
            "identifier": "mr.-men-1974-78-bbc-tv-series-the-complete-collection",
            "title": "Mr. Men",
            "desc": "Follows brightly colored characters that live in Misterland. All of them have names like Mr Happy, Mr Clumsy and Mr Greedy and their appearance and personality match their name.",
            "start": "1974",
            "end": "1983",
            "imdb": "tt0426754"
        },
        {
            "category": "kids",
            "status": "active",
            "identifier": "noddy-goes-to-toyland-1963-arthur-humberstone",
            "title": "Noddy Goes To Toyland",
            "desc": "This charming colour cartoon of Enid Blyton\u2019s timeless toy boy was produced as a pilot episode for an unrealised series. It is a faithful but curtailed version of Blyton\u2019s book of the same name, first published in 1949.",
            "start": "1963",
            "end": "1963",
            "imdb": "tt19815358"
        },
        {
            "category": "kids",
            "status": "active",
            "identifier": "wombles-1973-77",
            "title": "The Wombles",
            "desc": "The misadventures of a fantasy folk community dedicated to cleaning up litter and putting it to their own use.",
            "start": "1973",
            "end": "1975",
            "imdb": "tt0159227"
        },
        {
            "category": "kids",
            "status": "active",
            "identifier": "thomas-and-friends-the-complete-series-uk",
            "title": "Thomas and Friends",
            "desc": "This series follows the adventures of Thomas the Tank Engine and all of his engine friends on the Island of Sodor.",
            "start": "1984",
            "end": "2025",
            "imdb": "tt0086815"
        },
        {
            "category": "kids",
            "status": "active",
            "identifier": "ThunderbirdsSeries",
            "title": "Thunderbirds",
            "desc": "In the year 2065, the Tracy family run International Rescue - a top-secret organization whose ongoing mission is to rescue people trapped in extraordinarily dangerous situations using their advanced Thunderbirds machines.",
            "start": "1965",
            "end": "1966",
            "imdb": "tt0057790"
        },
        {
            "category": "kids",
            "status": "active",
            "identifier": "world-of-peter-rabbit-and-friends-1992-98",
            "title": "World of Peter Rabbit & Friends",
            "desc": "An animated series, telling the story of many beloved Beatrix Potter characters.",
            "start": "1992",
            "end": "1998",
            "imdb": "tt0296886"
        },
        {
            "category": "mystery",
            "status": "active",
            "identifier": "midsomer-murders-season1",
            "title": "Midsomer Murders Season 1",
            "desc": "A veteran Detective Chief Inspector and his young Sergeant investigate murders around the regional community of Midsomer County.",
            "start": "1997",
            "end": "2025",
            "imdb": "tt0118401",
            "group": "Midsomer Murders"
        },
        {
            "category": "mystery",
            "status": "active",
            "identifier": "midsomer-murders-season2",
            "title": "Midsomer Murders Season 2",
            "desc": "A veteran Detective Chief Inspector and his young Sergeant investigate murders around the regional community of Midsomer County.",
            "start": "1997",
            "end": "2025",
            "imdb": "tt0118401",
            "group": "Midsomer Murders"
        },
        {
            "category": "mystery",
            "status": "active",
            "identifier": "midsomer-murders-season3",
            "title": "Midsomer Murders Season 3",
            "desc": "A veteran Detective Chief Inspector and his young Sergeant investigate murders around the regional community of Midsomer County.",
            "start": "1997",
            "end": "2025",
            "imdb": "tt0118401",
            "group": "Midsomer Murders"
        },
        {
            "category": "mystery",
            "status": "active",
            "identifier": "SherlockHolmesGranada",
            "title": "Adventures of Sherlock Holmes",
            "desc": "Sherlock Holmes and Dr Watson solve the mysteries of copper beeches, a Greek interpreter, the Norwood builder, a resident patient, the red-headed league, and one final problem.",
            "start": "1984",
            "end": "1985",
            "imdb": "tt0086661"
        },
        {
            "category": "mystery",
            "status": "active",
            "identifier": "miss-marple-1984-92",
            "title": "Miss Marple",
            "desc": "Miss Marple, an elderly woman and amateur detective whose sharp mind helps her solve a series of seemingly baffling cases.",
            "start": "1984",
            "end": "1992",
            "imdb": "tt9907044"
        },
        {
            "category": "mystery",
            "status": "active",
            "identifier": "pie-in-the-sky-94-97",
            "title": "Pie in the Sky",
            "desc": "After a botched sting operation, and denied his imminent retirement, DI Crabbe is suspended from the police and opens his own restaurant. However, his ex-boss, Assistant Chief Constable Freddy Fisher, constantly calls him back on duty.",
            "start": "1994",
            "end": "1997",
            "imdb": "tt0106102"
        },
        {
            "category": "mystery",
            "status": "active",
            "identifier": "poirot-series",
            "title": "Poirot",
            "desc": "Hercule Poirot, a Belgian detective, has an impeccable knack for getting embroiled in a mystery and solving crimes.",
            "start": "1989",
            "end": "2013",
            "imdb": "tt0094525"
        },
        {
            "category": "mystery",
            "status": "active",
            "identifier": "BBC_Sherlock2010",
            "title": "Sherlock (2010)",
            "desc": "The quirky spin on Conan Doyle's iconic sleuth pitches him as a \"high-functioning sociopath\" in modern-day London. Assisting him in his investigations: Afghanistan War vet John Watson, who's introduced to Holmes by a mutual acquaintance.",
            "start": "2010",
            "end": "2017",
            "imdb": "tt1475582"
        },
        {
            "category": "sci-fi",
            "status": "active",
            "identifier": "doctor-who-2005-s01",
            "title": "Doctor Who (2005) Series 1",
            "desc": "Continuing on from Doctor Who (1963), this revival follows the further adventures of the Doctor and their companions as they encounter various alien threats and save civilizations on different planets and time periods.",
            "start": "2005",
            "end": "2007",
            "imdb": "tt0436992",
            "group": "Doctor Who (2005)"
        },
        {
            "category": "sci-fi",
            "status": "active",
            "identifier": "season-2-202315",
            "title": "Doctor Who (2005) Series 2",
            "desc": "Continuing on from Doctor Who (1963), this revival follows the further adventures of the Doctor and their companions as they encounter various alien threats and save civilizations on different planets and time periods.",
            "start": "2005",
            "end": "2007",
            "imdb": "tt0436992",
            "group": "Doctor Who (2005)"
        },
        {
            "category": "sci-fi",
            "status": "active",
            "identifier": "Space1999.Series1",
            "title": "Space 1999 Series 1",
            "desc": "Follows the crew of Moonbase Alpha who struggle to survive when a massive explosion throws the Moon from Earths orbit and out into deep space.",
            "start": "1975",
            "end": "1977",
            "imdb": "tt0072564",
            "group": "Space 1999"
        },
        {
            "category": "sci-fi",
            "status": "active",
            "identifier": "Space1999.Series1_201602",
            "title": "Space 1999 Series 2",
            "desc": "Follows the crew of Moonbase Alpha who struggle to survive when a massive explosion throws the Moon from Earths orbit and out into deep space.",
            "start": "1975",
            "end": "1977",
            "imdb": "tt0072564",
            "group": "Space 1999"
        },
        {
            "category": "sci-fi",
            "status": "active",
            "identifier": "doctor-who_202210",
            "title": "Doctor Who (1963)",
            "desc": "The adventures of 'The Doctor', a Time Lord who changes appearance and personality by regenerating when near death.",
            "start": "1963",
            "end": "1989",
            "imdb": "tt0056751"
        },
        {
            "category": "sci-fi",
            "status": "active",
            "identifier": "the-hitchhikers-guide-to-the-galaxy-complete-series-1981",
            "title": "Hitchhiker's Guide to the Galaxy",
            "desc": "Arthur Dent and his friend, Ford Prefect, escape the destruction of Earth, only to face incredible trials, tribulations and adventures in space and time.",
            "start": "1981",
            "end": "1981",
            "imdb": "tt0081874"
        },
        {
            "category": "sci-fi",
            "status": "active",
            "identifier": "UFO.complete",
            "title": "UFO",
            "desc": "In 1980, the Supreme Headquarters Alien Defence Organization covertly defends Earth against threats from a dying extraterrestrial race that needs to harvest human organs to survive.",
            "start": "1970",
            "end": "1971",
            "imdb": "tt0063962"
        },
        {
            "category": "Drama",
            "status": "active",
            "identifier": "tales-of-the-unexpected-1979-88",
            "title": "Tales of the Unexpected",
            "desc": "Short dramas each with a twist of some kind; across the first four seasons most of these are from short stories by Roald Dahl.",
            "start": "1979",
            "end": "1988",
            "imdb": "tt0075592"
        },
        {
            "category": "Drama",
            "status": "active",
            "identifier": "The_Prisoner",
            "title": "The Prisoner",
            "desc": "A former secret agent is abducted and taken to what looks like an idyllic village, but is actually a bizarre prison. He refuses to give his warders information while attempting to escape.",
            "start": "1967",
            "end": "1968",
            "imdb": "tt0061287"
        },
        {
            "category": "kids",
            "status": "active",
            "identifier": "animals-of-farthing-wood-1993-95",
            "title": "Animals of Farthing Wood",
            "desc": "A group of wild animal friends are forced to move to a park after humans drive them away from their old home.",
            "start": "1993",
            "end": "1995",
            "imdb": "tt0286336"
        },
        {
            "category": "kids",
            "status": "active",
            "identifier": "Stingray.Complete",
            "title": "Stingray",
            "desc": "In 2064, Captain Troy Tempest of the World Aquanaut Security Patrol and his crew explore the oceans in their combat submarine Stingray, encountering both friendly and hostile undersea aliens.",
            "start": "1964",
            "end": "1965",
            "imdb": "tt0057786"
        },
        {
            "category": "Drama",
            "status": "active",
            "identifier": "the-tomorrow-people-1973-79",
            "title": "The Tomorrow People",
            "desc": "A group of teens with psychic and other paranormal abilities use their special gifts to battle evil.",
            "start": "1973",
            "end": "1979",
            "imdb": "tt0069647"
        },
        {
            "category": "mystery",
            "status": "active",
            "identifier": "midsomer-murders-season4",
            "title": "Midsomer Murders Season 4",
            "desc": "A veteran Detective Chief Inspector and his young Sergeant investigate murders around the regional community of Midsomer County.",
            "start": "1997",
            "end": "2025",
            "imdb": "tt0118401",
            "group": "Midsomer Murders"
        },
        {
            "category": "comedy",
            "status": "active",
            "identifier": "it-aint-half-hot-mum-s-06-e-04-the-dhobi-wallahs",
            "title": "It Ain't Half Hot Mum",
            "desc": "The comic adventures of a group of misfits who form an extremely bad concert party touring the hot and steamy jungles of Burma entertaining the troops during World War II.",
            "start": "1974",
            "end": "1981",
            "imdb": "tt0081878"
        },
        {
            "category": "kids",
            "status": "active",
            "identifier": "Supercar.Series1",
            "title": "Supercar",
            "desc": "The adventures of Mike Mercury and the crew at Black Rock Laboratory in the Nevada Desert as they test out Supercar, a vehicle capable of traveling on land, underwater, and in the air.",
            "start": "1961",
            "end": "1962",
            "imdb": "tt0054567"
        },
        {
            "category": "kids",
            "status": "active",
            "identifier": "noddys-toyland-adventures-1992",
            "title": "Noddy's Toyland Adventures",
            "desc": "Young boy Noddy experiences adventures in Toyland, hosting parties for friends. Each episode features him finding a new toy and ends with a character getting \"goo'ed\" in fun mishaps.",
            "start": "1992",
            "end": "2000",
            "imdb": "tt0108881"
        },
        {
            "category": "sci-fi",
            "status": "active",
            "identifier": "star-cops-complete-series-1987",
            "title": "Star Cops",
            "desc": "Set in the year 2027 this follows the exploits of the fledgling International Space Police Force, nicknamed the \"Star Cops\".",
            "start": "1987",
            "end": "1987",
            "imdb": "tt0088613"
        },
        {
            "category": "Drama",
            "status": "active",
            "identifier": "ttss_20240201",
            "title": "Tinker, Tailor, Soldier, Spy",
            "desc": "In the bleak days of the Cold War, espionage veteran George Smiley is forced out of semi-retirement to uncover a Soviet agent within MI6's echelons.",
            "start": "1979",
            "end": "1979",
            "imdb": "tt0080297"
        },
        {
            "category": "Drama",
            "status": "active",
            "identifier": "dempsey-and-makepeace-complete-series-1985",
            "title": "Dempsey and Makepeace",
            "desc": "Dempsey, a tough NYPD cop, is sent to a London undercover police unit teamed up with the sophisticated, sexy, blonde Makepeace. They hunt down the top of London's underworld - when not quarreling.",
            "start": "1985",
            "end": "1986",
            "imdb": "tt0088503"
        },
        {
            "category": "mystery",
            "status": "active",
            "identifier": "father-brown-complete-series-1974",
            "title": "Father Brown",
            "desc": "Based on the stories of G.K. Chesterton, a British Catholic Priest solves mysteries.",
            "start": "1974",
            "end": "1974",
            "imdb": "tt0069582"
        },
        {
            "category": "Drama",
            "status": "active",
            "identifier": "raffles-complete-series-1975",
            "title": "Raffles",
            "desc": "A.J. Raffles, a gentleman cricketer, leads a double life as a jewel thief, aided by his friend Bunny Manders. He steals from the wealthy while occasionally playing detective across Edwardian England.",
            "start": "1975",
            "end": "1977",
            "imdb": "tt0075563"
        },
        {
            "category": "kids",
            "status": "active",
            "identifier": "into-the-labyrinth-Complete-series-1980",
            "title": "Into the Labyrinth",
            "desc": "Three children stumble upon the imprisoned sorcerer Rothgo and are drawn into a mysterious search through time for the magical Nidus which has been stolen by the evil witch Belor.",
            "start": "1981",
            "end": "1982",
            "imdb": "tt0081877"
        },
        {
            "category": "Drama",
            "status": "active",
            "identifier": "the-smuggler-complete-series-1981",
            "title": "Smuggler",
            "desc": "A former British naval officer turned smuggler navigates the espionage war between England and France in 1802, evading revenue officers while entangled in the clashing nations' covert operations.",
            "start": "1981",
            "end": "1981",
            "imdb": "tt0081932"
        },
        {
            "category": "sci-fi",
            "status": "active",
            "identifier": "the-invisible-man-1984_202505",
            "title": "The Invisible Man",
            "desc": "A scientist named Griffin invents a way to change his body's refractive index and thus becomes invisible. He uses the opportunity to carry out random acts of violence.",
            "start": "1984",
            "end": "1984",
            "imdb": "tt0087478"
        },
        {
            "category": "comedy",
            "status": "active",
            "identifier": "the-gaffer-complete-series-1981",
            "title": "The Gaffer",
            "desc": "The misadventures of Fred Moffatt (Bill Maynard), the owner of a run down light engineering firm, Moffat Engineering Company.",
            "start": "1981",
            "end": "1983",
            "imdb": "tt0081866"
        },
        {
            "category": "comedy",
            "status": "active",
            "identifier": "to-the-manor-born-season-1-of-3-tv-series-1979-xvid-avi",
            "title": "To The Manor Born Series 1",
            "desc": "Following her husband's passing, Audrey fforbes-Hamilton is forced to sell her stately home. While she comes to terms with her downward mobility, she decides to show the new owner a thing or two about \"nobility\". Series 1.",
            "start": "1979",
            "end": "1981",
            "imdb": "tt0078703",
            "group": "To The Manor Born"
        },
        {
            "category": "comedy",
            "status": "active",
            "identifier": "to-the-manor-born-season-2-of-3-tv-series-1979-xvid-avi",
            "title": "To The Manor Born Series 2",
            "desc": "Following her husband's passing, Audrey fforbes-Hamilton is forced to sell her stately home. While she comes to terms with her downward mobility, she decides to show the new owner a thing or two about \"nobility\". Series 2.",
            "start": "1979",
            "end": "1981",
            "imdb": "tt0078703",
            "group": "To The Manor Born"
        },
        {
            "category": "comedy",
            "status": "active",
            "identifier": "to-the-manor-born-season-3-of-3-tv-series-1979-xvid-avi",
            "title": "To The Manor Born Series 3",
            "desc": "Following her husband's passing, Audrey fforbes-Hamilton is forced to sell her stately home. While she comes to terms with her downward mobility, she decides to show the new owner a thing or two about \"nobility\".",
            "start": "1979",
            "end": "1981",
            "imdb": "tt0078703",
            "group": "To The Manor Born"
        },
        {
            "category": "comedy",
            "status": "active",
            "identifier": "to-the-manor-born-christmas-special-tv-series-1979-xvid-avi",
            "title": "Christmas Special (1979)",
            "desc": "Following her husband's passing, Audrey fforbes-Hamilton is forced to sell her stately home. While she comes to terms with her downward mobility, she decides to show the new owner a thing or two about \"nobility\". Christmas Special (1979).",
            "start": "1979",
            "end": "1981",
            "imdb": "tt0078703",
            "group": "To The Manor Born"
        },
        {
            "category": "comedy",
            "status": "active",
            "identifier": "youre-only-young-twice-1977-81",
            "title": "You're Only Young Twice",
            "desc": "Comedy about the residents of Paradise Lodge, retirement home for Gentle folk.",
            "start": "1977",
            "end": "1981",
            "imdb": "tt0075603"
        }
    ]
}